unidev/__init__.py
unidev/device_utils/__init__.py
unidev/device_utils/device.py
unidev/device_utils/serial/__init__.py
unidev/device_utils/serial/serial_device.py
unidev/device_utils/visa/__init__.py
unidev/device_utils/visa/visa_device.py
unidev/device_utils/visa/visa_model_device.py
unidev/model_utils/__init__.py
unidev/model_utils/model.py
unidev/model_utils/model_loader.py
unidev-0.0.3.2.dist-info/METADATA
unidev-0.0.3.2.dist-info/WHEEL
unidev-0.0.3.2.dist-info/top_level.txt
unidev-0.0.3.2.dist-info/RECORD
